ruireyan.py
axim-0.0.1.dist-info/LICENSE.txt
axim-0.0.1.dist-info/METADATA
axim-0.0.1.dist-info/WHEEL
axim-0.0.1.dist-info/top_level.txt
axim-0.0.1.dist-info/RECORD
