Metadata-Version: 2.1
Name: axim
Version: 0.0.1
Summary: reyan is sac
Home-page: https://github.com/ruireyan/
Author: reyan geelani
Author-email: reyangeelani@gmail.com
License-File: LICENSE.txt
